nonebot_plugin_nonememe-0.3.1.dist-info/METADATA
nonebot_plugin_nonememe-0.3.1.dist-info/WHEEL
nonebot_plugin_nonememe-0.3.1.dist-info/entry_points.txt
nonebot_plugin_nonememe-0.3.1.dist-info/licenses/LICENSE
nonebot_plugin_nonememe/__init__.py
nonebot_plugin_nonememe/__main__.py
nonebot_plugin_nonememe/config.py
nonebot_plugin_nonememe/data_source.py
nonebot_plugin_nonememe-0.3.1.dist-info/RECORD
