Metadata-Version: 2.1
Name: nonebot-plugin-nonememe
Version: 0.3.1
Summary: The daily life of the NoneBot group members
Author-Email: student_2333 <lgc2333@126.com>
License: MIT
Project-URL: homepage, https://github.com/lgc-NB2Dev/nonebot-plugin-nonememe
Requires-Python: <4.0,>=3.9
Requires-Dist: nonebot2>=2.3.1
Requires-Dist: nonebot-plugin-alconna>=0.48.0
Requires-Dist: nonebot-plugin-apscheduler>=0.5.0
Requires-Dist: httpx>=0.27.0
Requires-Dist: json5>=0.9.25
Requires-Dist: anyio>=4.4.0
Requires-Dist: typing-extensions>=4.12.2
